celery_sandbox/__init__.py
celery_sandbox/app.py
celery_sandbox/celeryconfig.py
celery_sandbox/tasks.py
celery_sandbox-0.2.0.dist-info/METADATA
celery_sandbox-0.2.0.dist-info/WHEEL
celery_sandbox-0.2.0.dist-info/top_level.txt
celery_sandbox-0.2.0.dist-info/RECORD
